classifier_calibration/__init__.py
classifier_calibration/calibration_error.py
classifier_calibration/classifier_calibration.py
classifier_calibration/utils.py
classifier_calibration-0.1.6.dist-info/AUTHORS.rst
classifier_calibration-0.1.6.dist-info/LICENSE
classifier_calibration-0.1.6.dist-info/METADATA
classifier_calibration-0.1.6.dist-info/WHEEL
classifier_calibration-0.1.6.dist-info/top_level.txt
classifier_calibration-0.1.6.dist-info/RECORD
