Metadata-Version: 2.1
Name: classifier-calibration
Version: 0.1.6
Summary: Python package to measure the calibration of probabilistic classifiers
Home-page: https://github.com/conor-walsh-cork/classifier_calibration
Author: Conor Walsh
Author-email: conorwalsh206@gmail.com
License: MIT license
Keywords: classifier_calibration
Platform: UNKNOWN
Classifier: Development Status :: 2 - Pre-Alpha
Classifier: Intended Audience :: Developers
Classifier: License :: OSI Approved :: MIT License
Classifier: Natural Language :: English
Classifier: Programming Language :: Python :: 3
Classifier: Programming Language :: Python :: 3.6
Classifier: Programming Language :: Python :: 3.7
Classifier: Programming Language :: Python :: 3.8
Requires-Python: >=3.6
License-File: LICENSE
License-File: AUTHORS.rst
Requires-Dist: pandas
Requires-Dist: numpy
